grpc_csm_observability/__init__.py
grpc_csm_observability/_csm_observability_plugin.py
grpcio_csm_observability-1.76.0.dist-info/LICENSE
grpcio_csm_observability-1.76.0.dist-info/METADATA
grpcio_csm_observability-1.76.0.dist-info/WHEEL
grpcio_csm_observability-1.76.0.dist-info/top_level.txt
grpcio_csm_observability-1.76.0.dist-info/RECORD
